[
  {
    "name": "Gedhe Leather Bali",
    "district": "Чангу",
    "category": "шоппинг",
    "budget": "💛",
    "price": "от 1M",
    "desc": "Казаки, ремни и обувь из натуральной кожи. Отшивают по вашим меркам прямо на Бали. Очень стильно и качественно.",
    "maps": "https://maps.google.com/maps/search/Gedhe+Leather+Bali",
    "vegan": false,
    "insta": false,
    "booking": false,
    "tags": [
      "одежда",
      "обувь",
      "$$"
    ]
  },
  {
    "name": "BURO Bali",
    "district": "Чангу",
    "category": "шоппинг",
    "budget": "💛",
    "price": "от 500K",
    "desc": "Стильные юбки, одежда и аксессуары. Концепт-стор с отличной селекцией балийских и международных дизайнеров.",
    "maps": "https://maps.google.com/maps/search/BURO+Bali",
    "vegan": false,
    "insta": false,
    "booking": false,
    "tags": [
      "одежда",
      "женское",
      "$$"
    ]
  },
  {
    "name": "Kevala Home Uluwatu (соседний магазин)",
    "district": "Улувату",
    "category": "шоппинг",
    "budget": "💛",
    "price": "от 300K",
    "desc": "Магазин рядом с Kevala Home в Улувату. Отличные купальники, джинсовки и пляжная одежда.",
    "maps": "https://maps.google.com/maps/search/Kevala+Home+Uluwatu",
    "vegan": false,
    "insta": false,
    "booking": false,
    "tags": [
      "одежда",
      "купальники",
      "женское",
      "$$"
    ]
  },
  {
    "name": "Balm Wears",
    "district": "Семиньяк",
    "category": "шоппинг",
    "budget": "💛",
    "desc": "Минималистичные блузы, платья и качественная базовая одежда из натуральных тканей. Идеально для балийской жары.",
    "maps": "https://maps.google.com/maps/search/Balm+Wears+Bali",
    "vegan": false,
    "insta": false,
    "booking": false,
    "tags": [
      "одежда",
      "женское",
      "$$"
    ]
  },
  {
    "name": "Cordero Gallery",
    "district": "Чангу",
    "category": "шоппинг",
    "budget": "💛",
    "desc": "Концепт-стор и галерея. Уникальные юбки, дизайнерские вещи и арт-объекты.",
    "maps": "https://maps.google.com/maps/search/Cordero+Gallery+Bali",
    "vegan": false,
    "insta": false,
    "booking": false,
    "tags": [
      "одежда",
      "женское",
      "$$"
    ]
  },
  {
    "name": "P53G C29 Jero (очищение и птицы)",
    "district": "bedugul",
    "category": "экспириенс",
    "budget": "по донату",
    "price": "донат",
    "maps": "https://maps.app.goo.gl/9ZzJJxvqwJMyY7RM6",
    "desc": "Скрытая жемчужина Бали — аутентичное кафе у местного дедушки (Мангку). Здесь живут экзотические птицы и животные, создавая атмосферу затерянного мира. Главная особенность: по вашему запросу дедушка может провести для вас настоящий балийский ритуал очищения (Мелукат) прямо на месте. Это очень камерный, глубокий и душевный опыт вдали от туристических толп. <b>📎 Мой совет:</b> оставляйте щедрый донат, это место держится на чистой энергии хозяина.",
    "tags": [
      "очищение",
      "животные",
      "кафе",
      "мелукат",
      "аутентично"
    ],
    "priority": 10
  }
]